cough/__init__.py
cough/file.py
cough/section.py
cough/string_table.py
cough/symbol.py
cough-0.2.1.dist-info/DESCRIPTION.rst
cough-0.2.1.dist-info/METADATA
cough-0.2.1.dist-info/RECORD
cough-0.2.1.dist-info/WHEEL
cough-0.2.1.dist-info/metadata.json
cough-0.2.1.dist-info/top_level.txt
