Metadata-Version: 2.0
Name: cough
Version: 0.2.1
Summary: Write COFF object files
Home-page: https://github.com/d3dave/cough
Author: David D. Dorfman
Author-email: d3dave@users.noreply.github.com
License: MIT
Keywords: coff pe obj build development
Platform: UNKNOWN
Classifier: Development Status :: 3 - Alpha
Classifier: Intended Audience :: Developers
Classifier: Topic :: Software Development
Classifier: License :: OSI Approved :: MIT License
Classifier: Programming Language :: Python :: 3
Classifier: Programming Language :: Python :: 3.6
Classifier: Operating System :: Microsoft :: Windows
